CHANGES.txt
LICENSE.txt
README.txt
bootstrap.py
buildout.cfg
setup.py
src/getpaid/__init__.py
src/getpaid.flatrateshipping.egg-info/PKG-INFO
src/getpaid.flatrateshipping.egg-info/SOURCES.txt
src/getpaid.flatrateshipping.egg-info/dependency_links.txt
src/getpaid.flatrateshipping.egg-info/namespace_packages.txt
src/getpaid.flatrateshipping.egg-info/not-zip-safe
src/getpaid.flatrateshipping.egg-info/requires.txt
src/getpaid.flatrateshipping.egg-info/top_level.txt
src/getpaid/flatrateshipping/README.txt
src/getpaid/flatrateshipping/__init__.py
src/getpaid/flatrateshipping/configure.zcml
src/getpaid/flatrateshipping/flatrate.py
src/getpaid/flatrateshipping/interfaces.py