Metadata-Version: 1.0
Name: getpaid.flatrateshipping
Version: 0.2
Summary: Get paid framework module for flat rate shipping
Home-page: http://code.google.com/p/getpaid
Author: Getpaid Community
Author-email: getpaid-dev@googlegroups.com
License: BSD
Platform: UNKNOWN
Classifier: Framework :: Plone
Classifier: Framework :: Zope3
Classifier: Programming Language :: Python
Classifier: Intended Audience :: Developers
Classifier: License :: OSI Approved :: Zope Public License
Classifier: Operating System :: OS Independent
Classifier: Topic :: Office/Business :: Financial
Classifier: Topic :: Software Development :: Libraries
